{
    "101CN": {
        "name": "Anhui",
        "sub": {
            "101201CN": "Fengyang",
            "101202CN": "Guangde",
            "101203CN": "Liuan",
            "101204CN": "Ningguo",
            "101205CN": "Shucheng",
            "101206CN": "Xinchang",
            "101207CN": "Xuancheng"
        }
    },
    "102CN": {
        "name": "Anhui Province",
        "sub": {
            "102201CN": "Fengyang",
            "102202CN": "Guangde",
            "102203CN": "Liuan",
            "102204CN": "Ningguo",
            "102205CN": "Shucheng",
            "102206CN": "Xinchang",
            "102207CN": "Xuancheng"
        }
    },
    "103CN": {
        "name": "Anhui Sheng",
        "sub": {
            "103201CN": "Fengyang",
            "103202CN": "Guangde",
            "103203CN": "Liuan",
            "103204CN": "Ningguo",
            "103205CN": "Shucheng",
            "103206CN": "Xinchang",
            "103207CN": "Xuancheng"
        }
    },
    "104CN": {
        "name": "Aomen",
        "sub": {
            "104201CN": "Aomen"
        }
    },
    "105CN": {
        "name": "Beijing",
        "sub": {
            "105201CN": "Beijing",
            "105202CN": "Changping",
            "105203CN": "Fangshan",
            "105204CN": "Huangcun",
            "105205CN": "Liangxiang",
            "105206CN": "Mentougou",
            "105207CN": "Shunyi",
            "105208CN": "Tongzhou"
        }
    },
    "106CN": {
        "name": "Beijing Shi",
        "sub": {
            "106201CN": "Beijing",
            "106202CN": "Changping",
            "106203CN": "Fangshan",
            "106204CN": "Huangcun",
            "106205CN": "Liangxiang",
            "106206CN": "Mentougou",
            "106207CN": "Shunyi",
            "106208CN": "Tongzhou"
        }
    },
    "107CN": {
        "name": "Chongqing",
        "sub": {
            "107201CN": "Beibei",
            "107202CN": "Chongqing",
            "107203CN": "Fuling",
            "107204CN": "Longhua",
            "107205CN": "Nantongkuang",
            "107206CN": "Wanxian",
            "107207CN": "Xiuma",
            "107208CN": "Yubei",
            "107209CN": "Yudong"
        }
    },
    "108CN": {
        "name": "Fujian",
        "sub": {
            "108201CN": "Bantou",
            "108202CN": "Dongshan",
            "108203CN": "Fuan",
            "108204CN": "Fujian",
            "108205CN": "Fuqing",
            "108206CN": "Fuzhou",
            "108207CN": "Gantou",
            "108208CN": "Hanyang",
            "108209CN": "Jiangkou",
            "108210CN": "Jiaocheng",
            "108211CN": "Jinjiang",
            "108212CN": "Jinshang",
            "108213CN": "Longhai",
            "108214CN": "Longyan",
            "108215CN": "Luoyang",
            "108216CN": "Nanan",
            "108217CN": "Nanping",
            "108218CN": "Nanpu",
            "108219CN": "Putian",
            "108220CN": "Qingyang",
            "108221CN": "Quanzhou",
            "108222CN": "Rongcheng",
            "108223CN": "Sanming",
            "108224CN": "Shaowu",
            "108225CN": "Shima",
            "108226CN": "Shishi",
            "108227CN": "Tantou",
            "108228CN": "Tongshan",
            "108229CN": "Xiamen",
            "108230CN": "Xiapu",
            "108231CN": "Xiapu Ningde",
            "108232CN": "Ximei",
            "108233CN": "Yongan",
            "108234CN": "Zhangzhou",
            "108235CN": "Zhicheng"
        }
    },
    "109CN": {
        "name": "Fujian Sheng",
        "sub": {
            "109201CN": "Bantou",
            "109202CN": "Dongshan",
            "109203CN": "Fuan",
            "109204CN": "Fujian",
            "109205CN": "Fuqing",
            "109206CN": "Fuzhou",
            "109207CN": "Gantou",
            "109208CN": "Hanyang",
            "109209CN": "Jiangkou",
            "109210CN": "Jiaocheng",
            "109211CN": "Jinjiang",
            "109212CN": "Jinshang",
            "109213CN": "Longhai",
            "109214CN": "Longyan",
            "109215CN": "Luoyang",
            "109216CN": "Nanan",
            "109217CN": "Nanping",
            "109218CN": "Nanpu",
            "109219CN": "Putian",
            "109220CN": "Qingyang",
            "109221CN": "Quanzhou",
            "109222CN": "Rongcheng",
            "109223CN": "Sanming",
            "109224CN": "Shaowu",
            "109225CN": "Shima",
            "109226CN": "Shishi",
            "109227CN": "Tantou",
            "109228CN": "Tongshan",
            "109229CN": "Xiamen",
            "109230CN": "Xiapu",
            "109231CN": "Xiapu Ningde",
            "109232CN": "Ximei",
            "109233CN": "Yongan",
            "109234CN": "Zhangzhou",
            "109235CN": "Zhicheng"
        }
    },
    "110CN": {
        "name": "Gansu",
        "sub": {
            "110201CN": "Baiyin",
            "110202CN": "Baoji",
            "110203CN": "Beidao",
            "110204CN": "Jiayuguan",
            "110205CN": "Jinchang",
            "110206CN": "Jiuquan",
            "110207CN": "Lanzhou",
            "110208CN": "Linxia",
            "110209CN": "Pingliang",
            "110210CN": "Qincheng",
            "110211CN": "Wuwei",
            "110212CN": "Yaojie",
            "110213CN": "Yumen",
            "110214CN": "Zhangye",
            "110215CN": "Zhuanglang"
        }
    },
    "111CN": {
        "name": "Guangdong",
        "sub": {
            "111201CN": "Anbu",
            "111202CN": "Chaozhou",
            "111203CN": "Chenghai",
            "111204CN": "Chuncheng",
            "111205CN": "Daliang",
            "111206CN": "Danshui",
            "111207CN": "Dongguan",
            "111208CN": "Donghai",
            "111209CN": "Dongli",
            "111210CN": "Dongzhen",
            "111211CN": "Ducheng",
            "111212CN": "Encheng",
            "111213CN": "Foahn",
            "111214CN": "Foshan",
            "111215CN": "Gaozhou",
            "111216CN": "Guangdong",
            "111217CN": "Guangzhou",
            "111218CN": "Guanjiao",
            "111219CN": "Haicheng",
            "111220CN": "Haimen",
            "111221CN": "Hepo",
            "111222CN": "Houpu",
            "111223CN": "Huaicheng",
            "111224CN": "Huanggang",
            "111225CN": "Huangpu",
            "111226CN": "Huazhou",
            "111227CN": "Huicheng",
            "111228CN": "Huizhou",
            "111229CN": "Humen",
            "111230CN": "Jiangmen",
            "111231CN": "Jiazi",
            "111232CN": "Jieshi",
            "111233CN": "Jieyang",
            "111234CN": "Lecheng",
            "111235CN": "Leicheng",
            "111236CN": "Liancheng",
            "111237CN": "Lianzhou",
            "111238CN": "Licheng",
            "111239CN": "Liusha",
            "111240CN": "Longgang",
            "111241CN": "Lubu",
            "111242CN": "Luocheng",
            "111243CN": "Luohu",
            "111244CN": "Luoyang",
            "111245CN": "Maba",
            "111246CN": "Maoming",
            "111247CN": "Mata",
            "111248CN": "Meilu",
            "111249CN": "Meizhou",
            "111250CN": "Mianchang",
            "111251CN": "Nanfeng",
            "111252CN": "Nanhai",
            "111253CN": "Pingshan",
            "111254CN": "Qingtang",
            "111255CN": "Qingyuan",
            "111256CN": "Rongcheng",
            "111257CN": "Sanbu",
            "111258CN": "Shantou",
            "111259CN": "Shanwei",
            "111260CN": "Shaoguan",
            "111261CN": "Shaping",
            "111262CN": "Shenzhen",
            "111263CN": "Shilong",
            "111264CN": "Shiqiao",
            "111265CN": "Shiwan",
            "111266CN": "Shuizhai",
            "111267CN": "Shunde",
            "111268CN": "Suicheng",
            "111269CN": "Taicheng",
            "111270CN": "Tangping",
            "111271CN": "Xiaolan",
            "111272CN": "Xinan",
            "111273CN": "Xingcheng",
            "111274CN": "Xiongzhou",
            "111275CN": "Xucheng",
            "111276CN": "Yangjiang",
            "111277CN": "Yingcheng",
            "111278CN": "Yuancheng",
            "111279CN": "Yuncheng",
            "111280CN": "Yunfu",
            "111281CN": "Zengcheng",
            "111282CN": "Zhanjiang",
            "111283CN": "Zhaoqing",
            "111284CN": "Zhilong",
            "111285CN": "Zhongshan",
            "111286CN": "Zhuhai"
        }
    },
    "112CN": {
        "name": "Guangdong Sheng",
        "sub": {
            "112201CN": "Anbu",
            "112202CN": "Chaozhou",
            "112203CN": "Chenghai",
            "112204CN": "Chuncheng",
            "112205CN": "Daliang",
            "112206CN": "Danshui",
            "112207CN": "Dongguan",
            "112208CN": "Donghai",
            "112209CN": "Dongli",
            "112210CN": "Dongzhen",
            "112211CN": "Ducheng",
            "112212CN": "Encheng",
            "112213CN": "Foahn",
            "112214CN": "Foshan",
            "112215CN": "Gaozhou",
            "112216CN": "Guangdong",
            "112217CN": "Guangzhou",
            "112218CN": "Guanjiao",
            "112219CN": "Haicheng",
            "112220CN": "Haimen",
            "112221CN": "Hepo",
            "112222CN": "Houpu",
            "112223CN": "Huaicheng",
            "112224CN": "Huanggang",
            "112225CN": "Huangpu",
            "112226CN": "Huazhou",
            "112227CN": "Huicheng",
            "112228CN": "Huizhou",
            "112229CN": "Humen",
            "112230CN": "Jiangmen",
            "112231CN": "Jiazi",
            "112232CN": "Jieshi",
            "112233CN": "Jieyang",
            "112234CN": "Lecheng",
            "112235CN": "Leicheng",
            "112236CN": "Liancheng",
            "112237CN": "Lianzhou",
            "112238CN": "Licheng",
            "112239CN": "Liusha",
            "112240CN": "Longgang",
            "112241CN": "Lubu",
            "112242CN": "Luocheng",
            "112243CN": "Luohu",
            "112244CN": "Luoyang",
            "112245CN": "Maba",
            "112246CN": "Maoming",
            "112247CN": "Mata",
            "112248CN": "Meilu",
            "112249CN": "Meizhou",
            "112250CN": "Mianchang",
            "112251CN": "Nanfeng",
            "112252CN": "Nanhai",
            "112253CN": "Pingshan",
            "112254CN": "Qingtang",
            "112255CN": "Qingyuan",
            "112256CN": "Rongcheng",
            "112257CN": "Sanbu",
            "112258CN": "Shantou",
            "112259CN": "Shanwei",
            "112260CN": "Shaoguan",
            "112261CN": "Shaping",
            "112262CN": "Shenzhen",
            "112263CN": "Shilong",
            "112264CN": "Shiqiao",
            "112265CN": "Shiwan",
            "112266CN": "Shuizhai",
            "112267CN": "Shunde",
            "112268CN": "Suicheng",
            "112269CN": "Taicheng",
            "112270CN": "Tangping",
            "112271CN": "Xiaolan",
            "112272CN": "Xinan",
            "112273CN": "Xingcheng",
            "112274CN": "Xiongzhou",
            "112275CN": "Xucheng",
            "112276CN": "Yangjiang",
            "112277CN": "Yingcheng",
            "112278CN": "Yuancheng",
            "112279CN": "Yuncheng",
            "112280CN": "Yunfu",
            "112281CN": "Zengcheng",
            "112282CN": "Zhanjiang",
            "112283CN": "Zhaoqing",
            "112284CN": "Zhilong",
            "112285CN": "Zhongshan",
            "112286CN": "Zhuhai"
        }
    },
    "113CN": {
        "name": "Guangxi",
        "sub": {
            "113201CN": "Babu",
            "113202CN": "Baihe",
            "113203CN": "Baise",
            "113204CN": "Beihai",
            "113205CN": "Binzhou",
            "113206CN": "Bose",
            "113207CN": "Fangchenggang",
            "113208CN": "Guicheng",
            "113209CN": "Guilin",
            "113210CN": "Guiping",
            "113211CN": "Jinchengjiang",
            "113212CN": "Jinji",
            "113213CN": "Laibin",
            "113214CN": "Lianzhou",
            "113215CN": "Liuzhou",
            "113216CN": "Luorong",
            "113217CN": "Matong",
            "113218CN": "Nandu",
            "113219CN": "Nanning",
            "113220CN": "Pingnan",
            "113221CN": "Pumiao",
            "113222CN": "Qinzhou",
            "113223CN": "Songhua",
            "113224CN": "Wuzhou",
            "113225CN": "Yashan",
            "113226CN": "Yulin"
        }
    },
    "114CN": {
        "name": "Guizhou",
        "sub": {
            "114201CN": "Anshun",
            "114202CN": "Bijie",
            "114203CN": "Caohai",
            "114204CN": "Duyun",
            "114205CN": "Guiyang",
            "114206CN": "Kaili",
            "114207CN": "Liupanshui",
            "114208CN": "Luoyang",
            "114209CN": "Pingzhai",
            "114210CN": "Tongren",
            "114211CN": "Tongzi",
            "114212CN": "Xiaoweizhai",
            "114213CN": "Xingyi",
            "114214CN": "Zunyi"
        }
    },
    "115CN": {
        "name": "Hainan",
        "sub": {
            "115201CN": "Chengmai",
            "115202CN": "Dingan",
            "115203CN": "Haikou",
            "115204CN": "Lingao",
            "115205CN": "Qiongshan",
            "115206CN": "Sansha ",
            "115207CN": "Sanya",
            "115208CN": "Wanning"
        }
    },
    "116CN": {
        "name": "Hebei",
        "sub": {
            "116201CN": "Anping",
            "116202CN": "Baoding",
            "116203CN": "Botou",
            "116204CN": "Cangzhou",
            "116205CN": "Changli",
            "116206CN": "Chengde",
            "116207CN": "Dingzhou",
            "116208CN": "Fengfeng",
            "116209CN": "Fengrun",
            "116210CN": "Guye",
            "116211CN": "Handan",
            "116212CN": "Hebei",
            "116213CN": "Hecun",
            "116214CN": "Hejian",
            "116215CN": "Hengshui",
            "116216CN": "Huanghua",
            "116217CN": "Jingxingkuang",
            "116218CN": "Jinzhou",
            "116219CN": "Langfang",
            "116220CN": "Lianzhou",
            "116221CN": "Linshui",
            "116222CN": "Linxi",
            "116223CN": "Longyao County",
            "116224CN": "Nangong",
            "116225CN": "Pengcheng",
            "116226CN": "Qinhuangdao",
            "116227CN": "Renqiu",
            "116228CN": "Shahe",
            "116229CN": "Shijiazhuang",
            "116230CN": "Tangjiazhuang",
            "116231CN": "Tangshan",
            "116232CN": "Wuan",
            "116233CN": "Xian County",
            "116234CN": "Xingtai",
            "116235CN": "Xinji",
            "116236CN": "Xinle",
            "116237CN": "Xuanhua",
            "116238CN": "Zhangjiakou",
            "116239CN": "Zhaogezhuang",
            "116240CN": "Zhuozhou"
        }
    },
    "117CN": {
        "name": "Heilongjiang",
        "sub": {
            "117201CN": "Acheng",
            "117202CN": "Anda",
            "117203CN": "Angangxi",
            "117204CN": "Baiquan",
            "117205CN": "Bamiantong",
            "117206CN": "Baoqing",
            "117207CN": "Baoshan",
            "117208CN": "Bayan",
            "117209CN": "Beian",
            "117210CN": "Binzhou",
            "117211CN": "Boli",
            "117212CN": "Chaihe",
            "117213CN": "Chengzihe",
            "117214CN": "Cuiluan",
            "117215CN": "Daqing",
            "117216CN": "Didao",
            "117217CN": "Dongning",
            "117218CN": "Fujin",
            "117219CN": "Fuli",
            "117220CN": "Fulitun",
            "117221CN": "Fuyu",
            "117222CN": "Gannan",
            "117223CN": "Hailin",
            "117224CN": "Hailun",
            "117225CN": "Harbin",
            "117226CN": "Hegang",
            "117227CN": "Heihe",
            "117228CN": "Hengshan",
            "117229CN": "Honggang",
            "117230CN": "Huanan",
            "117231CN": "Hulan",
            "117232CN": "Hulan Ergi",
            "117233CN": "Jiamusi",
            "117234CN": "Jidong",
            "117235CN": "Jixi",
            "117236CN": "Keshan",
            "117237CN": "Langxiang",
            "117238CN": "Lanxi",
            "117239CN": "Lingdong",
            "117240CN": "Linkou",
            "117241CN": "Lishu",
            "117242CN": "Longfeng",
            "117243CN": "Longjiang",
            "117244CN": "Mingshui",
            "117245CN": "Mishan",
            "117246CN": "Mudanjiang",
            "117247CN": "Nancha",
            "117248CN": "Nehe",
            "117249CN": "Nenjiang",
            "117250CN": "Nianzishan",
            "117251CN": "Ningan",
            "117252CN": "Qingan",
            "117253CN": "Qinggang",
            "117254CN": "Qiqihar",
            "117255CN": "Qitaihe",
            "117256CN": "Ranghulu",
            "117257CN": "Saertu",
            "117258CN": "Shangzhi",
            "117259CN": "Shanhetun",
            "117260CN": "Shuangcheng",
            "117261CN": "Shuangyashan",
            "117262CN": "Sifantan",
            "117263CN": "Suifenhe",
            "117264CN": "Suihua",
            "117265CN": "Suileng",
            "117266CN": "Tahe",
            "117267CN": "Taikang",
            "117268CN": "Tailai",
            "117269CN": "Tieli",
            "117270CN": "Wangkui",
            "117271CN": "Weihe",
            "117272CN": "Wuchang",
            "117273CN": "Xinglongzhen",
            "117274CN": "Xinqing",
            "117275CN": "Yian",
            "117276CN": "Yichun",
            "117277CN": "Yilan",
            "117278CN": "Youhao",
            "117279CN": "Zhaodong",
            "117280CN": "Zhaoyuan",
            "117281CN": "Zhaozhou"
        }
    },
    "118CN": {
        "name": "Henan",
        "sub": {
            "118201CN": "Anyang",
            "118202CN": "Changying",
            "118203CN": "Dancheng",
            "118204CN": "Daokou",
            "118205CN": "Dengzhou",
            "118206CN": "Gongyi",
            "118207CN": "Gushi",
            "118208CN": "Hebi",
            "118209CN": "Huaidian",
            "118210CN": "Huangchuan",
            "118211CN": "Huangzhai",
            "118212CN": "Jiaozuo",
            "118213CN": "Jishui",
            "118214CN": "Kaifeng",
            "118215CN": "Liupen",
            "118216CN": "Luohe",
            "118217CN": "Luoyang",
            "118218CN": "Luyang",
            "118219CN": "Mengzhou",
            "118220CN": "Minggang",
            "118221CN": "Nandun",
            "118222CN": "Nanyang",
            "118223CN": "Pingdingshan",
            "118224CN": "Puyang",
            "118225CN": "Sanmenxia",
            "118226CN": "Shangqiu",
            "118227CN": "Tanghe",
            "118228CN": "Xiaoyi",
            "118229CN": "Xihua",
            "118230CN": "Xinxiang",
            "118231CN": "Xinyang",
            "118232CN": "Xinye",
            "118233CN": "Xixiang",
            "118234CN": "Xuanwu",
            "118235CN": "Xuchang",
            "118236CN": "Yigou",
            "118237CN": "Yima",
            "118238CN": "Yinzhuang",
            "118239CN": "Yunyang",
            "118240CN": "Yuzhou",
            "118241CN": "Zhecheng",
            "118242CN": "Zhengzhou",
            "118243CN": "Zhenping",
            "118244CN": "Zhoukou",
            "118245CN": "Zhumadian"
        }
    },
    "119CN": {
        "name": "Hubei",
        "sub": {
            "119201CN": "Anlu",
            "119202CN": "Baisha",
            "119203CN": "Buhe",
            "119204CN": "Caidian",
            "119205CN": "Caohe",
            "119206CN": "Danjiangkou",
            "119207CN": "Daye",
            "119208CN": "Duobao",
            "119209CN": "Enshi",
            "119210CN": "Ezhou",
            "119211CN": "Fengkou",
            "119212CN": "Guangshui",
            "119213CN": "Gucheng",
            "119214CN": "Hanchuan",
            "119215CN": "Hongan",
            "119216CN": "Honghu",
            "119217CN": "Huangmei",
            "119218CN": "Huangpi",
            "119219CN": "Huangshi",
            "119220CN": "Huangzhou",
            "119221CN": "Jingmen",
            "119222CN": "Jingzhou",
            "119223CN": "Laohekou",
            "119224CN": "Lichuan",
            "119225CN": "Macheng",
            "119226CN": "Nanhai",
            "119227CN": "Nanzhang",
            "119228CN": "Puqi",
            "119229CN": "Qianjiang",
            "119230CN": "Qingquan",
            "119231CN": "Qixingtai",
            "119232CN": "Rongcheng",
            "119233CN": "Shashi",
            "119234CN": "Shishou",
            "119235CN": "Shiyan",
            "119236CN": "Suizhou",
            "119237CN": "Tianmen",
            "119238CN": "Tongcheng",
            "119239CN": "Wuhan",
            "119240CN": "Wuxue",
            "119241CN": "Xiangfan",
            "119242CN": "Xianning",
            "119243CN": "Xiantao",
            "119244CN": "Xiaogan",
            "119245CN": "Xiaoxita",
            "119246CN": "Xiaxindian",
            "119247CN": "Xihe",
            "119248CN": "Xinpu",
            "119249CN": "Xinshi",
            "119250CN": "Xinzhou",
            "119251CN": "Yichang",
            "119252CN": "Yicheng",
            "119253CN": "Yingcheng",
            "119254CN": "Yingzhong",
            "119255CN": "Zaoyang",
            "119256CN": "Zhengchang",
            "119257CN": "Zhicheng",
            "119258CN": "Zhifang",
            "119259CN": "Zhongxiang"
        }
    },
    "120CN": {
        "name": "Hunan",
        "sub": {
            "120201CN": "Anjiang",
            "120202CN": "Anxiang",
            "120203CN": "Changde",
            "120204CN": "Changsha",
            "120205CN": "Chenzhou",
            "120206CN": "Dayong",
            "120207CN": "Hengyang",
            "120208CN": "Hongjiang",
            "120209CN": "Huaihua",
            "120210CN": "Jinshi",
            "120211CN": "Jishou",
            "120212CN": "Leiyang",
            "120213CN": "Lengshuijiang",
            "120214CN": "Lengshuitan",
            "120215CN": "Lianyuan",
            "120216CN": "Liling",
            "120217CN": "Liuyang",
            "120218CN": "Loudi",
            "120219CN": "Matian",
            "120220CN": "Nanzhou",
            "120221CN": "Ningxiang",
            "120222CN": "Qidong",
            "120223CN": "Qiyang",
            "120224CN": "Shaoyang",
            "120225CN": "Xiangtan",
            "120226CN": "Xiangxiang",
            "120227CN": "Xiangyin",
            "120228CN": "Xinhua",
            "120229CN": "Yiyang",
            "120230CN": "Yongfeng",
            "120231CN": "Yongzhou",
            "120232CN": "Yuanjiang",
            "120233CN": "Yueyang",
            "120234CN": "Zhuzhou"
        }
    },
    "121CN": {
        "name": "Jiangsu",
        "sub": {
            "121201CN": "Baoying",
            "121202CN": "Changzhou",
            "121203CN": "Dachang",
            "121204CN": "Dafeng",
            "121205CN": "Danyang",
            "121206CN": "Dingshu",
            "121207CN": "Dongkan",
            "121208CN": "Dongtai",
            "121209CN": "Fengxian",
            "121210CN": "Gaogou",
            "121211CN": "Gaoyou",
            "121212CN": "Guiren",
            "121213CN": "Haian",
            "121214CN": "Haizhou",
            "121215CN": "Hede",
            "121216CN": "Huaicheng",
            "121217CN": "Huaiyin",
            "121218CN": "Huilong",
            "121219CN": "Hutang",
            "121220CN": "Jiangdu",
            "121221CN": "Jiangyan",
            "121222CN": "Jiangyin",
            "121223CN": "Jiangyuan",
            "121224CN": "Jianhu",
            "121225CN": "Jingcheng",
            "121226CN": "Jinsha",
            "121227CN": "Jintan",
            "121228CN": "Juegang",
            "121229CN": "Jurong",
            "121230CN": "Kunshan",
            "121231CN": "Lianyungang",
            "121232CN": "Liucheng",
            "121233CN": "Liyang",
            "121234CN": "Luodu",
            "121235CN": "Mudu",
            "121236CN": "Nanjing",
            "121237CN": "Nantong",
            "121238CN": "Pecheng",
            "121239CN": "Pukou",
            "121240CN": "Qidong",
            "121241CN": "Qinnan",
            "121242CN": "Qixia",
            "121243CN": "Rucheng",
            "121244CN": "Songling",
            "121245CN": "Sucheng",
            "121246CN": "Suicheng",
            "121247CN": "Suqian",
            "121248CN": "Suzhou",
            "121249CN": "Taicang",
            "121250CN": "Taixing",
            "121251CN": "Wujiang",
            "121252CN": "Wuxi",
            "121253CN": "Xiaolingwei",
            "121254CN": "Xiaoshi",
            "121255CN": "Xinan",
            "121256CN": "Xinpu",
            "121257CN": "Xuzhou",
            "121258CN": "Yancheng",
            "121259CN": "Yangshe",
            "121260CN": "Yangzhou",
            "121261CN": "Yizheng",
            "121262CN": "Yunhe",
            "121263CN": "Yunyang",
            "121264CN": "Yushan",
            "121265CN": "Zhangjiagang",
            "121266CN": "Zhangjiangang",
            "121267CN": "Zhaoyang",
            "121268CN": "Zhenjiang",
            "121269CN": "Zhongxing"
        }
    },
    "122CN": {
        "name": "Jiangsu Sheng",
        "sub": {
            "122201CN": "Baoying",
            "122202CN": "Changzhou",
            "122203CN": "Dachang",
            "122204CN": "Dafeng",
            "122205CN": "Danyang",
            "122206CN": "Dingshu",
            "122207CN": "Dongkan",
            "122208CN": "Dongtai",
            "122209CN": "Fengxian",
            "122210CN": "Gaogou",
            "122211CN": "Gaoyou",
            "122212CN": "Guiren",
            "122213CN": "Haian",
            "122214CN": "Haizhou",
            "122215CN": "Hede",
            "122216CN": "Huaicheng",
            "122217CN": "Huaiyin",
            "122218CN": "Huilong",
            "122219CN": "Hutang",
            "122220CN": "Jiangdu",
            "122221CN": "Jiangyan",
            "122222CN": "Jiangyin",
            "122223CN": "Jiangyuan",
            "122224CN": "Jianhu",
            "122225CN": "Jingcheng",
            "122226CN": "Jinsha",
            "122227CN": "Jintan",
            "122228CN": "Juegang",
            "122229CN": "Jurong",
            "122230CN": "Kunshan",
            "122231CN": "Lianyungang",
            "122232CN": "Liucheng",
            "122233CN": "Liyang",
            "122234CN": "Luodu",
            "122235CN": "Mudu",
            "122236CN": "Nanjing",
            "122237CN": "Nantong",
            "122238CN": "Pecheng",
            "122239CN": "Pukou",
            "122240CN": "Qidong",
            "122241CN": "Qinnan",
            "122242CN": "Qixia",
            "122243CN": "Rucheng",
            "122244CN": "Songling",
            "122245CN": "Sucheng",
            "122246CN": "Suicheng",
            "122247CN": "Suqian",
            "122248CN": "Suzhou",
            "122249CN": "Taicang",
            "122250CN": "Taixing",
            "122251CN": "Wujiang",
            "122252CN": "Wuxi",
            "122253CN": "Xiaolingwei",
            "122254CN": "Xiaoshi",
            "122255CN": "Xinan",
            "122256CN": "Xinpu",
            "122257CN": "Xuzhou",
            "122258CN": "Yancheng",
            "122259CN": "Yangshe",
            "122260CN": "Yangzhou",
            "122261CN": "Yizheng",
            "122262CN": "Yunhe",
            "122263CN": "Yunyang",
            "122264CN": "Yushan",
            "122265CN": "Zhangjiagang",
            "122266CN": "Zhangjiangang",
            "122267CN": "Zhaoyang",
            "122268CN": "Zhenjiang",
            "122269CN": "Zhongxing"
        }
    },
    "123CN": {
        "name": "Jiangxi",
        "sub": {
            "123201CN": "Fengxin",
            "123202CN": "Fenyi",
            "123203CN": "Ganzhou",
            "123204CN": "Jian",
            "123205CN": "Jiangguang",
            "123206CN": "Jingdezhen",
            "123207CN": "Jiujiang",
            "123208CN": "Leping",
            "123209CN": "Linchuan",
            "123210CN": "Nanchang",
            "123211CN": "Pingxiang",
            "123212CN": "Poyang",
            "123213CN": "Shangrao",
            "123214CN": "Xiangdong",
            "123215CN": "Xingan",
            "123216CN": "Xinjian",
            "123217CN": "Xinyu",
            "123218CN": "Xiongshi",
            "123219CN": "Yichun",
            "123220CN": "Yingtai",
            "123221CN": "Yingtan",
            "123222CN": "Zhangshui"
        }
    },
    "124CN": {
        "name": "Jilin",
        "sub": {
            "124201CN": "Badaojiang",
            "124202CN": "Baicheng",
            "124203CN": "Baishishan",
            "124204CN": "Changchun",
            "124205CN": "Changling",
            "124206CN": "Chaoyang",
            "124207CN": "Daan",
            "124208CN": "Dashitou",
            "124209CN": "Dehui",
            "124210CN": "Dongchang",
            "124211CN": "Dongfeng",
            "124212CN": "Dunhua",
            "124213CN": "Erdaojiang",
            "124214CN": "Fuyu",
            "124215CN": "Gongzhuling",
            "124216CN": "Helong",
            "124217CN": "Hongmei",
            "124218CN": "Huadian",
            "124219CN": "Huangnihe",
            "124220CN": "Huinan",
            "124221CN": "Hunchun",
            "124222CN": "Jiaohe",
            "124223CN": "Jilin",
            "124224CN": "Jishu",
            "124225CN": "Jiutai",
            "124226CN": "Kaitong",
            "124227CN": "Kouqian",
            "124228CN": "Liaoyuan",
            "124229CN": "Linjiang",
            "124230CN": "Lishu",
            "124231CN": "Liuhe",
            "124232CN": "Longjing",
            "124233CN": "Meihekou",
            "124234CN": "Mingyue",
            "124235CN": "Nongan",
            "124236CN": "Panshi",
            "124237CN": "Pizhou",
            "124238CN": "Qianan",
            "124239CN": "Qianguo",
            "124240CN": "Sanchazi",
            "124241CN": "Shuangyang",
            "124242CN": "Shulan",
            "124243CN": "Siping",
            "124244CN": "Songjianghe",
            "124245CN": "Taonan",
            "124246CN": "Tumen",
            "124247CN": "Wangou",
            "124248CN": "Wangqing",
            "124249CN": "Xinglongshan",
            "124250CN": "Yanji",
            "124251CN": "Yantongshan",
            "124252CN": "Yushu",
            "124253CN": "Zhengjiatun",
            "124254CN": "Zhenlai"
        }
    },
    "125CN": {
        "name": "Liaoning",
        "sub": {
            "125201CN": "Anshan",
            "125202CN": "Beipiao",
            "125203CN": "Benxi",
            "125204CN": "Changtu",
            "125205CN": "Chaoyang",
            "125206CN": "Dalian",
            "125207CN": "Dalianwan",
            "125208CN": "Dalinghe",
            "125209CN": "Dandong",
            "125210CN": "Dashiqiao",
            "125211CN": "Dongling",
            "125212CN": "Fengcheng",
            "125213CN": "Fushun",
            "125214CN": "Fuxin",
            "125215CN": "Haicheng",
            "125216CN": "Heishan",
            "125217CN": "Huanren",
            "125218CN": "Huludao",
            "125219CN": "Hushitai",
            "125220CN": "Jinxi",
            "125221CN": "Jinzhou",
            "125222CN": "Jiupu",
            "125223CN": "Kaiyuan",
            "125224CN": "Kuandian",
            "125225CN": "Langtou",
            "125226CN": "Liaoyang",
            "125227CN": "Liaozhong",
            "125228CN": "Lingyuan",
            "125229CN": "Liuerbao",
            "125230CN": "Lushunkou",
            "125231CN": "Nantai",
            "125232CN": "Panjin",
            "125233CN": "Pulandian",
            "125234CN": "Shenyang",
            "125235CN": "Sujiatun",
            "125236CN": "Tieling",
            "125237CN": "Wafangdian",
            "125238CN": "Xiaoshi",
            "125239CN": "Xifeng",
            "125240CN": "Xinchengxi",
            "125241CN": "Xingcheng",
            "125242CN": "Xinmin",
            "125243CN": "Xiongyue",
            "125244CN": "Xiuyan",
            "125245CN": "Yebaishou",
            "125246CN": "Yingkou",
            "125247CN": "Yuhong",
            "125248CN": "Zhuanghe"
        }
    },
    "126CN": {
        "name": "Liaoning Sheng",
        "sub": {
            "126201CN": "Anshan",
            "126202CN": "Beipiao",
            "126203CN": "Benxi",
            "126204CN": "Changtu",
            "126205CN": "Chaoyang",
            "126206CN": "Dalian",
            "126207CN": "Dalianwan",
            "126208CN": "Dalinghe",
            "126209CN": "Dandong",
            "126210CN": "Dashiqiao",
            "126211CN": "Dongling",
            "126212CN": "Fengcheng",
            "126213CN": "Fushun",
            "126214CN": "Fuxin",
            "126215CN": "Haicheng",
            "126216CN": "Heishan",
            "126217CN": "Huanren",
            "126218CN": "Huludao",
            "126219CN": "Hushitai",
            "126220CN": "Jinxi",
            "126221CN": "Jinzhou",
            "126222CN": "Jiupu",
            "126223CN": "Kaiyuan",
            "126224CN": "Kuandian",
            "126225CN": "Langtou",
            "126226CN": "Liaoyang",
            "126227CN": "Liaozhong",
            "126228CN": "Lingyuan",
            "126229CN": "Liuerbao",
            "126230CN": "Lushunkou",
            "126231CN": "Nantai",
            "126232CN": "Panjin",
            "126233CN": "Pulandian",
            "126234CN": "Shenyang",
            "126235CN": "Sujiatun",
            "126236CN": "Tieling",
            "126237CN": "Wafangdian",
            "126238CN": "Xiaoshi",
            "126239CN": "Xifeng",
            "126240CN": "Xinchengxi",
            "126241CN": "Xingcheng",
            "126242CN": "Xinmin",
            "126243CN": "Xiongyue",
            "126244CN": "Xiuyan",
            "126245CN": "Yebaishou",
            "126246CN": "Yingkou",
            "126247CN": "Yuhong",
            "126248CN": "Zhuanghe"
        }
    },
    "127CN": {
        "name": "Nei Monggol",
        "sub": {
            "127201CN": "Anshan",
            "127202CN": "Beipiao",
            "127203CN": "Benxi",
            "127204CN": "Changtu",
            "127205CN": "Chaoyang",
            "127206CN": "Dalian",
            "127207CN": "Dalianwan",
            "127208CN": "Dalinghe",
            "127209CN": "Dandong",
            "127210CN": "Dashiqiao",
            "127211CN": "Dongling",
            "127212CN": "Fengcheng",
            "127213CN": "Fushun",
            "127214CN": "Fuxin",
            "127215CN": "Haicheng",
            "127216CN": "Heishan",
            "127217CN": "Huanren",
            "127218CN": "Huludao",
            "127219CN": "Hushitai",
            "127220CN": "Jinxi",
            "127221CN": "Jinzhou",
            "127222CN": "Jiupu",
            "127223CN": "Kaiyuan",
            "127224CN": "Kuandian",
            "127225CN": "Langtou",
            "127226CN": "Liaoyang",
            "127227CN": "Liaozhong",
            "127228CN": "Lingyuan",
            "127229CN": "Liuerbao",
            "127230CN": "Lushunkou",
            "127231CN": "Nantai",
            "127232CN": "Panjin",
            "127233CN": "Pulandian",
            "127234CN": "Shenyang",
            "127235CN": "Sujiatun",
            "127236CN": "Tieling",
            "127237CN": "Wafangdian",
            "127238CN": "Xiaoshi",
            "127239CN": "Xifeng",
            "127240CN": "Xinchengxi",
            "127241CN": "Xingcheng",
            "127242CN": "Xinmin",
            "127243CN": "Xiongyue",
            "127244CN": "Xiuyan",
            "127245CN": "Yebaishou",
            "127246CN": "Yingkou",
            "127247CN": "Yuhong",
            "127248CN": "Zhuanghe"
        }
    },
    "128CN": {
        "name": "Ningxia Hui",
        "sub": {
            "128201CN": "Anshan",
            "128202CN": "Beipiao",
            "128203CN": "Benxi",
            "128204CN": "Changtu",
            "128205CN": "Chaoyang",
            "128206CN": "Dalian",
            "128207CN": "Dalianwan",
            "128208CN": "Dalinghe",
            "128209CN": "Dandong",
            "128210CN": "Dashiqiao",
            "128211CN": "Dongling",
            "128212CN": "Fengcheng",
            "128213CN": "Fushun",
            "128214CN": "Fuxin",
            "128215CN": "Haicheng",
            "128216CN": "Heishan",
            "128217CN": "Huanren",
            "128218CN": "Huludao",
            "128219CN": "Hushitai",
            "128220CN": "Jinxi",
            "128221CN": "Jinzhou",
            "128222CN": "Jiupu",
            "128223CN": "Kaiyuan",
            "128224CN": "Kuandian",
            "128225CN": "Langtou",
            "128226CN": "Liaoyang",
            "128227CN": "Liaozhong",
            "128228CN": "Lingyuan",
            "128229CN": "Liuerbao",
            "128230CN": "Lushunkou",
            "128231CN": "Nantai",
            "128232CN": "Panjin",
            "128233CN": "Pulandian",
            "128234CN": "Shenyang",
            "128235CN": "Sujiatun",
            "128236CN": "Tieling",
            "128237CN": "Wafangdian",
            "128238CN": "Xiaoshi",
            "128239CN": "Xifeng",
            "128240CN": "Xinchengxi",
            "128241CN": "Xingcheng",
            "128242CN": "Xinmin",
            "128243CN": "Xiongyue",
            "128244CN": "Xiuyan",
            "128245CN": "Yebaishou",
            "128246CN": "Yingkou",
            "128247CN": "Yuhong",
            "128248CN": "Zhuanghe"
        }
    },
    "129CN": {
        "name": "Qinghai",
        "sub": {
            "129201CN": "Qiatou",
            "129202CN": "Xining"
        }
    },
    "130CN": {
        "name": "Shaanxi",
        "sub": {
            "130201CN": "Ankang",
            "130202CN": "Baoji",
            "130203CN": "Guozhen",
            "130204CN": "Hancheng",
            "130205CN": "Hanzhong",
            "130206CN": "Lishan",
            "130207CN": "Qili",
            "130208CN": "Tongchuan",
            "130209CN": "Weinan",
            "130210CN": "Xian",
            "130211CN": "Xianyang",
            "130212CN": "Yanan",
            "130213CN": "Yanliang",
            "130214CN": "Yulin",
            "130215CN": "Yuxia"
        }
    },
    "131CN": {
        "name": "Shandong",
        "sub": {
            "131201CN": "Anqiu",
            "131202CN": "Bianzhuang",
            "131203CN": "Binzhou",
            "131204CN": "Boshan",
            "131205CN": "Boxing County",
            "131206CN": "Caocheng",
            "131207CN": "Changqing",
            "131208CN": "Chengyang",
            "131209CN": "Dengzhou",
            "131210CN": "Dezhou",
            "131211CN": "Dingtao",
            "131212CN": "Dongcun",
            "131213CN": "Dongdu",
            "131214CN": "Donge County",
            "131215CN": "Dongying",
            "131216CN": "Feicheng",
            "131217CN": "Fushan",
            "131218CN": "Gaomi",
            "131219CN": "Haiyang",
            "131220CN": "Hanting",
            "131221CN": "Hekou",
            "131222CN": "Heze",
            "131223CN": "Jiaonan",
            "131224CN": "Jiaozhou",
            "131225CN": "Jiehu",
            "131226CN": "Jimo",
            "131227CN": "Jinan",
            "131228CN": "Jining",
            "131229CN": "Juxian",
            "131230CN": "Juye",
            "131231CN": "Kunlun",
            "131232CN": "Laiwu",
            "131233CN": "Laiyang",
            "131234CN": "Laizhou",
            "131235CN": "Leling",
            "131236CN": "Liaocheng",
            "131237CN": "Licung",
            "131238CN": "Linqing",
            "131239CN": "Linqu",
            "131240CN": "Linshu",
            "131241CN": "Linyi",
            "131242CN": "Longkou",
            "131243CN": "Mengyin",
            "131244CN": "Mingshui",
            "131245CN": "Nanchou",
            "131246CN": "Nanding",
            "131247CN": "Nanma",
            "131248CN": "Ninghai",
            "131249CN": "Ningyang",
            "131250CN": "Pingdu",
            "131251CN": "Pingyi",
            "131252CN": "Pingyin",
            "131253CN": "Qingdao",
            "131254CN": "Qingzhou",
            "131255CN": "Qixia",
            "131256CN": "Qufu",
            "131257CN": "Rizhao",
            "131258CN": "Rongcheng",
            "131259CN": "Shancheng",
            "131260CN": "Shanting",
            "131261CN": "Shengzhuang",
            "131262CN": "Shenxian",
            "131263CN": "Shizilu",
            "131264CN": "Shouguang",
            "131265CN": "Shuiji",
            "131266CN": "Sishui",
            "131267CN": "Suozhen",
            "131268CN": "Taian",
            "131269CN": "Tancheng",
            "131270CN": "Taozhuang",
            "131271CN": "Tengzhou",
            "131272CN": "Weifang",
            "131273CN": "Weihai",
            "131274CN": "Wencheng",
            "131275CN": "Wendeng",
            "131276CN": "Wenshang",
            "131277CN": "Wudi",
            "131278CN": "Xiazhen",
            "131279CN": "Xincheng",
            "131280CN": "Xindian",
            "131281CN": "Xintai",
            "131282CN": "Yanggu",
            "131283CN": "Yangshan",
            "131284CN": "Yantai",
            "131285CN": "Yanzhou",
            "131286CN": "Yatou",
            "131287CN": "Yidu",
            "131288CN": "Yishui",
            "131289CN": "Yucheng",
            "131290CN": "Yuncheng",
            "131291CN": "Zaozhuang",
            "131292CN": "Zhangdian",
            "131293CN": "Zhangjiawa",
            "131294CN": "Zhangqiu",
            "131295CN": "Zhaocheng",
            "131296CN": "Zhoucheng",
            "131297CN": "Zhoucun",
            "131298CN": "Zhucheng",
            "131299CN": "Zhuwang",
            "1312100CN": "Zicheng",
            "1312101CN": "Zouping",
            "1312102CN": "Zouxian"
        }
    },
    "132CN": {
        "name": "Shandong Sheng",
        "sub": {
            "132201CN": "Anqiu",
            "132202CN": "Bianzhuang",
            "132203CN": "Binzhou",
            "132204CN": "Boshan",
            "132205CN": "Boxing County",
            "132206CN": "Caocheng",
            "132207CN": "Changqing",
            "132208CN": "Chengyang",
            "132209CN": "Dengzhou",
            "132210CN": "Dezhou",
            "132211CN": "Dingtao",
            "132212CN": "Dongcun",
            "132213CN": "Dongdu",
            "132214CN": "Donge County",
            "132215CN": "Dongying",
            "132216CN": "Feicheng",
            "132217CN": "Fushan",
            "132218CN": "Gaomi",
            "132219CN": "Haiyang",
            "132220CN": "Hanting",
            "132221CN": "Hekou",
            "132222CN": "Heze",
            "132223CN": "Jiaonan",
            "132224CN": "Jiaozhou",
            "132225CN": "Jiehu",
            "132226CN": "Jimo",
            "132227CN": "Jinan",
            "132228CN": "Jining",
            "132229CN": "Juxian",
            "132230CN": "Juye",
            "132231CN": "Kunlun",
            "132232CN": "Laiwu",
            "132233CN": "Laiyang",
            "132234CN": "Laizhou",
            "132235CN": "Leling",
            "132236CN": "Liaocheng",
            "132237CN": "Licung",
            "132238CN": "Linqing",
            "132239CN": "Linqu",
            "132240CN": "Linshu",
            "132241CN": "Linyi",
            "132242CN": "Longkou",
            "132243CN": "Mengyin",
            "132244CN": "Mingshui",
            "132245CN": "Nanchou",
            "132246CN": "Nanding",
            "132247CN": "Nanma",
            "132248CN": "Ninghai",
            "132249CN": "Ningyang",
            "132250CN": "Pingdu",
            "132251CN": "Pingyi",
            "132252CN": "Pingyin",
            "132253CN": "Qingdao",
            "132254CN": "Qingzhou",
            "132255CN": "Qixia",
            "132256CN": "Qufu",
            "132257CN": "Rizhao",
            "132258CN": "Rongcheng",
            "132259CN": "Shancheng",
            "132260CN": "Shanting",
            "132261CN": "Shengzhuang",
            "132262CN": "Shenxian",
            "132263CN": "Shizilu",
            "132264CN": "Shouguang",
            "132265CN": "Shuiji",
            "132266CN": "Sishui",
            "132267CN": "Suozhen",
            "132268CN": "Taian",
            "132269CN": "Tancheng",
            "132270CN": "Taozhuang",
            "132271CN": "Tengzhou",
            "132272CN": "Weifang",
            "132273CN": "Weihai",
            "132274CN": "Wencheng",
            "132275CN": "Wendeng",
            "132276CN": "Wenshang",
            "132277CN": "Wudi",
            "132278CN": "Xiazhen",
            "132279CN": "Xincheng",
            "132280CN": "Xindian",
            "132281CN": "Xintai",
            "132282CN": "Yanggu",
            "132283CN": "Yangshan",
            "132284CN": "Yantai",
            "132285CN": "Yanzhou",
            "132286CN": "Yatou",
            "132287CN": "Yidu",
            "132288CN": "Yishui",
            "132289CN": "Yucheng",
            "132290CN": "Yuncheng",
            "132291CN": "Zaozhuang",
            "132292CN": "Zhangdian",
            "132293CN": "Zhangjiawa",
            "132294CN": "Zhangqiu",
            "132295CN": "Zhaocheng",
            "132296CN": "Zhoucheng",
            "132297CN": "Zhoucun",
            "132298CN": "Zhucheng",
            "132299CN": "Zhuwang",
            "1322100CN": "Zicheng",
            "1322101CN": "Zouping",
            "1322102CN": "Zouxian"
        }
    },
    "133CN": {
        "name": "Shanghai",
        "sub": {
            "133201CN": "Jiading",
            "133202CN": "Minhang",
            "133203CN": "Shanghai",
            "133204CN": "Songjiang",
            "133205CN": "Trencin"
        }
    },
    "134CN": {
        "name": "Shanxi",
        "sub": {
            "134201CN": "Changzhi",
            "134202CN": "Datong",
            "134203CN": "Houma",
            "134204CN": "Jiexiu",
            "134205CN": "Jincheng",
            "134206CN": "Linfen",
            "134207CN": "Taiyuan",
            "134208CN": "Xian",
            "134209CN": "Xinzhi",
            "134210CN": "Xinzhou",
            "134211CN": "Yangquan",
            "134212CN": "Yuanping",
            "134213CN": "Yuci",
            "134214CN": "Yuncheng"
        }
    },
    "135CN": {
        "name": "Sichuan",
        "sub": {
            "135201CN": "Anju",
            "135202CN": "Baoning",
            "135203CN": "Chengdu",
            "135204CN": "Daan",
            "135205CN": "Dawan",
            "135206CN": "Daxian",
            "135207CN": "Deyang",
            "135208CN": "Dujiangyan City",
            "135209CN": "Guangkou",
            "135210CN": "Guangyuan",
            "135211CN": "Guihu",
            "135212CN": "Heyang",
            "135213CN": "Huayang",
            "135214CN": "Jiancheng",
            "135215CN": "Jiangyou",
            "135216CN": "Jijiang",
            "135217CN": "Leshan",
            "135218CN": "Linqiong",
            "135219CN": "Luocheng",
            "135220CN": "Luzhou",
            "135221CN": "Mianyang",
            "135222CN": "Nanchong",
            "135223CN": "Nanlong",
            "135224CN": "Neijiang",
            "135225CN": "Panzhihua",
            "135226CN": "Shifang",
            "135227CN": "Suining",
            "135228CN": "Taihe",
            "135229CN": "Tianpeng",
            "135230CN": "Tongchuan",
            "135231CN": "Xichang",
            "135232CN": "Xunchang",
            "135233CN": "Yaan",
            "135234CN": "Yibin",
            "135235CN": "Yongchang",
            "135236CN": "Zhonglong",
            "135237CN": "Zigong",
            "135238CN": "Ziyang"
        }
    },
    "136CN": {
        "name": "Tianjin",
        "sub": {
            "136201CN": "Beichen",
            "136202CN": "Gangdong",
            "136203CN": "Hangu",
            "136204CN": "Jinghai",
            "136205CN": "Nankai",
            "136206CN": "Tanggu",
            "136207CN": "Tianjin",
            "136208CN": "Xianshuigu",
            "136209CN": "Yangcun",
            "136210CN": "Yangliuqing"
        }
    },
    "137CN": {
        "name": "Xianggang",
        "sub": {
            "137201CN": "Guiqing",
            "137202CN": "Jiulong",
            "137203CN": "Quanwan",
            "137204CN": "Saigong",
            "137205CN": "Shatin",
            "137206CN": "Taipo",
            "137207CN": "Tuanmun",
            "137208CN": "Xianggang",
            "137209CN": "Yuanlong"
        }
    },
    "138CN": {
        "name": "Xinjiang",
        "sub": {
            "138201CN": "Aksu",
            "138202CN": "Baijiantan",
            "138203CN": "Changji",
            "138204CN": "Dongshan",
            "138205CN": "Hami",
            "138206CN": "Hetian",
            "138207CN": "Karamay",
            "138208CN": "Kashi",
            "138209CN": "Korla",
            "138210CN": "Kuche",
            "138211CN": "Kuytun",
            "138212CN": "Shache",
            "138213CN": "Shihezi",
            "138214CN": "Shuimogou",
            "138215CN": "Toutunhe",
            "138216CN": "Urumqi",
            "138217CN": "Yining"
        }
    },
    "139CN": {
        "name": "Xizang",
        "sub": {
            "139201CN": "Lasa"
        }
    },
    "140CN": {
        "name": "Yunnan",
        "sub": {
            "140201CN": "Dali",
            "140202CN": "Gejiu",
            "140203CN": "Haikou",
            "140204CN": "Heilin",
            "140205CN": "Jinma",
            "140206CN": "Kaihua",
            "140207CN": "Kaiyuan",
            "140208CN": "Kunming",
            "140209CN": "Lianran",
            "140210CN": "Longquan",
            "140211CN": "Lucheng",
            "140212CN": "Mabai",
            "140213CN": "Majie",
            "140214CN": "Miyang",
            "140215CN": "Qujing",
            "140216CN": "Rongcheng",
            "140217CN": "Simao",
            "140218CN": "Wufeng",
            "140219CN": "Yunjinghong",
            "140220CN": "Yuxi Municipal",
            "140221CN": "Zhaotong",
            "140222CN": "Zhenhai",
            "140223CN": "Zhongshu",
            "140224CN": "Zhoucheng",
            "140225CN": "Zhuocheng"
        }
    },
    "141CN": {
        "name": "Zhejiang",
        "sub": {
            "141201CN": "Aojiang",
            "141202CN": "Choucheng",
            "141203CN": "Cixi",
            "141204CN": "Daqiao",
            "141205CN": "Deqing",
            "141206CN": "Dinghai",
            "141207CN": "Dongyang",
            "141208CN": "fenghua",
            "141209CN": "Fuyang",
            "141210CN": "Haining",
            "141211CN": "Haiyan",
            "141212CN": "Hangzhou",
            "141213CN": "Huangyan",
            "141214CN": "Hushan",
            "141215CN": "Huzhou",
            "141216CN": "Jiaojiang",
            "141217CN": "jiashan",
            "141218CN": "Jiaxing",
            "141219CN": "Jinhua",
            "141220CN": "Jinxiang",
            "141221CN": "Kaihua",
            "141222CN": "Kunyang",
            "141223CN": "Lanxi",
            "141224CN": "Linan City",
            "141225CN": "Linhai",
            "141226CN": "Linping",
            "141227CN": "Lishui",
            "141228CN": "Liushi",
            "141229CN": "Ningbo",
            "141230CN": "Ninghai",
            "141231CN": "Pinghu",
            "141232CN": "Quzhou",
            "141233CN": "Ruian",
            "141234CN": "Shangyu",
            "141235CN": "Shaoxing",
            "141236CN": "Shenjiamen",
            "141237CN": "Taizhou City",
            "141238CN": "Tonglu",
            "141239CN": "Wenling",
            "141240CN": "Wenzhou",
            "141241CN": "Wuning",
            "141242CN": "Wuyi",
            "141243CN": "Xianju",
            "141244CN": "Xiaoshan",
            "141245CN": "Xiashi",
            "141246CN": "Xushan",
            "141247CN": "Yiwu",
            "141248CN": "Yongkang",
            "141249CN": "Yueqing",
            "141250CN": "Yuhuan",
            "141251CN": "Yuyao",
            "141252CN": "Zhejiang",
            "141253CN": "Zhenhai",
            "141254CN": "Zhicheng",
            "141255CN": "Zhuji"
        }
    },
    "142CN": {
        "name": "Zhejiang Sheng",
        "sub": {
            "142201CN": "Aojiang",
            "142202CN": "Choucheng",
            "142203CN": "Cixi",
            "142204CN": "Daqiao",
            "142205CN": "Deqing",
            "142206CN": "Dinghai",
            "142207CN": "Dongyang",
            "142208CN": "fenghua",
            "142209CN": "Fuyang",
            "142210CN": "Haining",
            "142211CN": "Haiyan",
            "142212CN": "Hangzhou",
            "142213CN": "Huangyan",
            "142214CN": "Hushan",
            "142215CN": "Huzhou",
            "142216CN": "Jiaojiang",
            "142217CN": "jiashan",
            "142218CN": "Jiaxing",
            "142219CN": "Jinhua",
            "142220CN": "Jinxiang",
            "142221CN": "Kaihua",
            "142222CN": "Kunyang",
            "142223CN": "Lanxi",
            "142224CN": "Linan City",
            "142225CN": "Linhai",
            "142226CN": "Linping",
            "142227CN": "Lishui",
            "142228CN": "Liushi",
            "142229CN": "Ningbo",
            "142230CN": "Ninghai",
            "142231CN": "Pinghu",
            "142232CN": "Quzhou",
            "142233CN": "Ruian",
            "142234CN": "Shangyu",
            "142235CN": "Shaoxing",
            "142236CN": "Shenjiamen",
            "142237CN": "Taizhou City",
            "142238CN": "Tonglu",
            "142239CN": "Wenling",
            "142240CN": "Wenzhou",
            "142241CN": "Wuning",
            "142242CN": "Wuyi",
            "142243CN": "Xianju",
            "142244CN": "Xiaoshan",
            "142245CN": "Xiashi",
            "142246CN": "Xushan",
            "142247CN": "Yiwu",
            "142248CN": "Yongkang",
            "142249CN": "Yueqing",
            "142250CN": "Yuhuan",
            "142251CN": "Yuyao",
            "142252CN": "Zhejiang",
            "142253CN": "Zhenhai",
            "142254CN": "Zhicheng",
            "142255CN": "Zhuji"
        }
    }
}