{
    "101IM": {
        "name": "Castletown",
        "sub": {
            "101201IM": "Acquaviva delle Fonti",
            "101202IM": "Adelfia",
            "101203IM": "Alberobello",
            "101204IM": "Altamura",
            "101205IM": "Andria",
            "101206IM": "Apricena",
            "101207IM": "Aradeo",
            "101208IM": "Bari",
            "101209IM": "Barletta",
            "101210IM": "Bisceglie",
            "101211IM": "Bitetto",
            "101212IM": "Bitonto",
            "101213IM": "Bitritto",
            "101214IM": "Brindisi",
            "101215IM": "Campi Salentina",
            "101216IM": "Canosa di Puglia",
            "101217IM": "Capurso",
            "101218IM": "Carmiano",
            "101219IM": "Carovigno",
            "101220IM": "Casamassima",
            "101221IM": "Casarano",
            "101222IM": "Cassano delle Murge",
            "101223IM": "Castellana Grotte",
            "101224IM": "Castellaneta",
            "101225IM": "Cavallino",
            "101226IM": "Ceglie Messapica",
            "101227IM": "Cerignola",
            "101228IM": "Cisternino",
            "101229IM": "Conversano",
            "101230IM": "Copertino",
            "101231IM": "Corato",
            "101232IM": "Crispiano",
            "101233IM": "Cutrofiano",
            "101234IM": "Erchie",
            "101235IM": "Fasano",
            "101236IM": "Foggia",
            "101237IM": "Francavilla Fontana",
            "101238IM": "Galatina",
            "101239IM": "Galatone",
            "101240IM": "Gallipoli",
            "101241IM": "Ginosa",
            "101242IM": "Gioia del Colle",
            "101243IM": "Giovinazzo",
            "101244IM": "Gravina in Puglia",
            "101245IM": "Grottaglie",
            "101246IM": "Grumo Appula",
            "101247IM": "Laterza",
            "101248IM": "Latiano",
            "101249IM": "Lecce",
            "101250IM": "Leverano",
            "101251IM": "Lizzanello",
            "101252IM": "Lizzano",
            "101253IM": "Locorotondo",
            "101254IM": "Lucera",
            "101255IM": "Maglie",
            "101256IM": "Manduria",
            "101257IM": "Manfredonia",
            "101258IM": "Margherita di Savoia",
            "101259IM": "Martano",
            "101260IM": "Martina Franca",
            "101261IM": "Massafra",
            "101262IM": "Matino",
            "101263IM": "Melendugno",
            "101264IM": "Mesagne",
            "101265IM": "Minervino Murge",
            "101266IM": "Modugno",
            "101267IM": "Mola di Bari",
            "101268IM": "Molfetta",
            "101269IM": "Monopoli",
            "101270IM": "Monte Sant\\'Angelo",
            "101271IM": "Monteroni di Lecce",
            "101272IM": "Mottola",
            "101273IM": "Nardo",
            "101274IM": "Neviano",
            "101275IM": "Noci",
            "101276IM": "Noicattaro",
            "101277IM": "Novoli",
            "101278IM": "Oria",
            "101279IM": "Orta Nova",
            "101280IM": "Ostuni",
            "101281IM": "Palagiano",
            "101282IM": "Palo del Colle",
            "101283IM": "Parabita",
            "101284IM": "Polignano a Mare",
            "101285IM": "Pulsano",
            "101286IM": "Putignano"
        }
    },
    "102IM": {
        "name": "Douglas",
        "sub": {
            "102201IM": "Acquaviva delle Fonti",
            "102202IM": "Adelfia",
            "102203IM": "Alberobello",
            "102204IM": "Altamura",
            "102205IM": "Andria",
            "102206IM": "Apricena",
            "102207IM": "Aradeo",
            "102208IM": "Bari",
            "102209IM": "Barletta",
            "102210IM": "Bisceglie",
            "102211IM": "Bitetto",
            "102212IM": "Bitonto",
            "102213IM": "Bitritto",
            "102214IM": "Brindisi",
            "102215IM": "Campi Salentina",
            "102216IM": "Canosa di Puglia",
            "102217IM": "Capurso",
            "102218IM": "Carmiano",
            "102219IM": "Carovigno",
            "102220IM": "Casamassima",
            "102221IM": "Casarano",
            "102222IM": "Cassano delle Murge",
            "102223IM": "Castellana Grotte",
            "102224IM": "Castellaneta",
            "102225IM": "Cavallino",
            "102226IM": "Ceglie Messapica",
            "102227IM": "Cerignola",
            "102228IM": "Cisternino",
            "102229IM": "Conversano",
            "102230IM": "Copertino",
            "102231IM": "Corato",
            "102232IM": "Crispiano",
            "102233IM": "Cutrofiano",
            "102234IM": "Erchie",
            "102235IM": "Fasano",
            "102236IM": "Foggia",
            "102237IM": "Francavilla Fontana",
            "102238IM": "Galatina",
            "102239IM": "Galatone",
            "102240IM": "Gallipoli",
            "102241IM": "Ginosa",
            "102242IM": "Gioia del Colle",
            "102243IM": "Giovinazzo",
            "102244IM": "Gravina in Puglia",
            "102245IM": "Grottaglie",
            "102246IM": "Grumo Appula",
            "102247IM": "Laterza",
            "102248IM": "Latiano",
            "102249IM": "Lecce",
            "102250IM": "Leverano",
            "102251IM": "Lizzanello",
            "102252IM": "Lizzano",
            "102253IM": "Locorotondo",
            "102254IM": "Lucera",
            "102255IM": "Maglie",
            "102256IM": "Manduria",
            "102257IM": "Manfredonia",
            "102258IM": "Margherita di Savoia",
            "102259IM": "Martano",
            "102260IM": "Martina Franca",
            "102261IM": "Massafra",
            "102262IM": "Matino",
            "102263IM": "Melendugno",
            "102264IM": "Mesagne",
            "102265IM": "Minervino Murge",
            "102266IM": "Modugno",
            "102267IM": "Mola di Bari",
            "102268IM": "Molfetta",
            "102269IM": "Monopoli",
            "102270IM": "Monte Sant\\'Angelo",
            "102271IM": "Monteroni di Lecce",
            "102272IM": "Mottola",
            "102273IM": "Nardo",
            "102274IM": "Neviano",
            "102275IM": "Noci",
            "102276IM": "Noicattaro",
            "102277IM": "Novoli",
            "102278IM": "Oria",
            "102279IM": "Orta Nova",
            "102280IM": "Ostuni",
            "102281IM": "Palagiano",
            "102282IM": "Palo del Colle",
            "102283IM": "Parabita",
            "102284IM": "Polignano a Mare",
            "102285IM": "Pulsano",
            "102286IM": "Putignano"
        }
    },
    "103IM": {
        "name": "Laxey",
        "sub": {
            "103201IM": "Acquaviva delle Fonti",
            "103202IM": "Adelfia",
            "103203IM": "Alberobello",
            "103204IM": "Altamura",
            "103205IM": "Andria",
            "103206IM": "Apricena",
            "103207IM": "Aradeo",
            "103208IM": "Bari",
            "103209IM": "Barletta",
            "103210IM": "Bisceglie",
            "103211IM": "Bitetto",
            "103212IM": "Bitonto",
            "103213IM": "Bitritto",
            "103214IM": "Brindisi",
            "103215IM": "Campi Salentina",
            "103216IM": "Canosa di Puglia",
            "103217IM": "Capurso",
            "103218IM": "Carmiano",
            "103219IM": "Carovigno",
            "103220IM": "Casamassima",
            "103221IM": "Casarano",
            "103222IM": "Cassano delle Murge",
            "103223IM": "Castellana Grotte",
            "103224IM": "Castellaneta",
            "103225IM": "Cavallino",
            "103226IM": "Ceglie Messapica",
            "103227IM": "Cerignola",
            "103228IM": "Cisternino",
            "103229IM": "Conversano",
            "103230IM": "Copertino",
            "103231IM": "Corato",
            "103232IM": "Crispiano",
            "103233IM": "Cutrofiano",
            "103234IM": "Erchie",
            "103235IM": "Fasano",
            "103236IM": "Foggia",
            "103237IM": "Francavilla Fontana",
            "103238IM": "Galatina",
            "103239IM": "Galatone",
            "103240IM": "Gallipoli",
            "103241IM": "Ginosa",
            "103242IM": "Gioia del Colle",
            "103243IM": "Giovinazzo",
            "103244IM": "Gravina in Puglia",
            "103245IM": "Grottaglie",
            "103246IM": "Grumo Appula",
            "103247IM": "Laterza",
            "103248IM": "Latiano",
            "103249IM": "Lecce",
            "103250IM": "Leverano",
            "103251IM": "Lizzanello",
            "103252IM": "Lizzano",
            "103253IM": "Locorotondo",
            "103254IM": "Lucera",
            "103255IM": "Maglie",
            "103256IM": "Manduria",
            "103257IM": "Manfredonia",
            "103258IM": "Margherita di Savoia",
            "103259IM": "Martano",
            "103260IM": "Martina Franca",
            "103261IM": "Massafra",
            "103262IM": "Matino",
            "103263IM": "Melendugno",
            "103264IM": "Mesagne",
            "103265IM": "Minervino Murge",
            "103266IM": "Modugno",
            "103267IM": "Mola di Bari",
            "103268IM": "Molfetta",
            "103269IM": "Monopoli",
            "103270IM": "Monte Sant\\'Angelo",
            "103271IM": "Monteroni di Lecce",
            "103272IM": "Mottola",
            "103273IM": "Nardo",
            "103274IM": "Neviano",
            "103275IM": "Noci",
            "103276IM": "Noicattaro",
            "103277IM": "Novoli",
            "103278IM": "Oria",
            "103279IM": "Orta Nova",
            "103280IM": "Ostuni",
            "103281IM": "Palagiano",
            "103282IM": "Palo del Colle",
            "103283IM": "Parabita",
            "103284IM": "Polignano a Mare",
            "103285IM": "Pulsano",
            "103286IM": "Putignano"
        }
    },
    "104IM": {
        "name": "Onchan",
        "sub": {
            "104201IM": "Acquaviva delle Fonti",
            "104202IM": "Adelfia",
            "104203IM": "Alberobello",
            "104204IM": "Altamura",
            "104205IM": "Andria",
            "104206IM": "Apricena",
            "104207IM": "Aradeo",
            "104208IM": "Bari",
            "104209IM": "Barletta",
            "104210IM": "Bisceglie",
            "104211IM": "Bitetto",
            "104212IM": "Bitonto",
            "104213IM": "Bitritto",
            "104214IM": "Brindisi",
            "104215IM": "Campi Salentina",
            "104216IM": "Canosa di Puglia",
            "104217IM": "Capurso",
            "104218IM": "Carmiano",
            "104219IM": "Carovigno",
            "104220IM": "Casamassima",
            "104221IM": "Casarano",
            "104222IM": "Cassano delle Murge",
            "104223IM": "Castellana Grotte",
            "104224IM": "Castellaneta",
            "104225IM": "Cavallino",
            "104226IM": "Ceglie Messapica",
            "104227IM": "Cerignola",
            "104228IM": "Cisternino",
            "104229IM": "Conversano",
            "104230IM": "Copertino",
            "104231IM": "Corato",
            "104232IM": "Crispiano",
            "104233IM": "Cutrofiano",
            "104234IM": "Erchie",
            "104235IM": "Fasano",
            "104236IM": "Foggia",
            "104237IM": "Francavilla Fontana",
            "104238IM": "Galatina",
            "104239IM": "Galatone",
            "104240IM": "Gallipoli",
            "104241IM": "Ginosa",
            "104242IM": "Gioia del Colle",
            "104243IM": "Giovinazzo",
            "104244IM": "Gravina in Puglia",
            "104245IM": "Grottaglie",
            "104246IM": "Grumo Appula",
            "104247IM": "Laterza",
            "104248IM": "Latiano",
            "104249IM": "Lecce",
            "104250IM": "Leverano",
            "104251IM": "Lizzanello",
            "104252IM": "Lizzano",
            "104253IM": "Locorotondo",
            "104254IM": "Lucera",
            "104255IM": "Maglie",
            "104256IM": "Manduria",
            "104257IM": "Manfredonia",
            "104258IM": "Margherita di Savoia",
            "104259IM": "Martano",
            "104260IM": "Martina Franca",
            "104261IM": "Massafra",
            "104262IM": "Matino",
            "104263IM": "Melendugno",
            "104264IM": "Mesagne",
            "104265IM": "Minervino Murge",
            "104266IM": "Modugno",
            "104267IM": "Mola di Bari",
            "104268IM": "Molfetta",
            "104269IM": "Monopoli",
            "104270IM": "Monte Sant\\'Angelo",
            "104271IM": "Monteroni di Lecce",
            "104272IM": "Mottola",
            "104273IM": "Nardo",
            "104274IM": "Neviano",
            "104275IM": "Noci",
            "104276IM": "Noicattaro",
            "104277IM": "Novoli",
            "104278IM": "Oria",
            "104279IM": "Orta Nova",
            "104280IM": "Ostuni",
            "104281IM": "Palagiano",
            "104282IM": "Palo del Colle",
            "104283IM": "Parabita",
            "104284IM": "Polignano a Mare",
            "104285IM": "Pulsano",
            "104286IM": "Putignano"
        }
    },
    "105IM": {
        "name": "Peel",
        "sub": {
            "105201IM": "Acquaviva delle Fonti",
            "105202IM": "Adelfia",
            "105203IM": "Alberobello",
            "105204IM": "Altamura",
            "105205IM": "Andria",
            "105206IM": "Apricena",
            "105207IM": "Aradeo",
            "105208IM": "Bari",
            "105209IM": "Barletta",
            "105210IM": "Bisceglie",
            "105211IM": "Bitetto",
            "105212IM": "Bitonto",
            "105213IM": "Bitritto",
            "105214IM": "Brindisi",
            "105215IM": "Campi Salentina",
            "105216IM": "Canosa di Puglia",
            "105217IM": "Capurso",
            "105218IM": "Carmiano",
            "105219IM": "Carovigno",
            "105220IM": "Casamassima",
            "105221IM": "Casarano",
            "105222IM": "Cassano delle Murge",
            "105223IM": "Castellana Grotte",
            "105224IM": "Castellaneta",
            "105225IM": "Cavallino",
            "105226IM": "Ceglie Messapica",
            "105227IM": "Cerignola",
            "105228IM": "Cisternino",
            "105229IM": "Conversano",
            "105230IM": "Copertino",
            "105231IM": "Corato",
            "105232IM": "Crispiano",
            "105233IM": "Cutrofiano",
            "105234IM": "Erchie",
            "105235IM": "Fasano",
            "105236IM": "Foggia",
            "105237IM": "Francavilla Fontana",
            "105238IM": "Galatina",
            "105239IM": "Galatone",
            "105240IM": "Gallipoli",
            "105241IM": "Ginosa",
            "105242IM": "Gioia del Colle",
            "105243IM": "Giovinazzo",
            "105244IM": "Gravina in Puglia",
            "105245IM": "Grottaglie",
            "105246IM": "Grumo Appula",
            "105247IM": "Laterza",
            "105248IM": "Latiano",
            "105249IM": "Lecce",
            "105250IM": "Leverano",
            "105251IM": "Lizzanello",
            "105252IM": "Lizzano",
            "105253IM": "Locorotondo",
            "105254IM": "Lucera",
            "105255IM": "Maglie",
            "105256IM": "Manduria",
            "105257IM": "Manfredonia",
            "105258IM": "Margherita di Savoia",
            "105259IM": "Martano",
            "105260IM": "Martina Franca",
            "105261IM": "Massafra",
            "105262IM": "Matino",
            "105263IM": "Melendugno",
            "105264IM": "Mesagne",
            "105265IM": "Minervino Murge",
            "105266IM": "Modugno",
            "105267IM": "Mola di Bari",
            "105268IM": "Molfetta",
            "105269IM": "Monopoli",
            "105270IM": "Monte Sant\\'Angelo",
            "105271IM": "Monteroni di Lecce",
            "105272IM": "Mottola",
            "105273IM": "Nardo",
            "105274IM": "Neviano",
            "105275IM": "Noci",
            "105276IM": "Noicattaro",
            "105277IM": "Novoli",
            "105278IM": "Oria",
            "105279IM": "Orta Nova",
            "105280IM": "Ostuni",
            "105281IM": "Palagiano",
            "105282IM": "Palo del Colle",
            "105283IM": "Parabita",
            "105284IM": "Polignano a Mare",
            "105285IM": "Pulsano",
            "105286IM": "Putignano"
        }
    },
    "106IM": {
        "name": "Port Erin",
        "sub": {
            "106201IM": "Acquaviva delle Fonti",
            "106202IM": "Adelfia",
            "106203IM": "Alberobello",
            "106204IM": "Altamura",
            "106205IM": "Andria",
            "106206IM": "Apricena",
            "106207IM": "Aradeo",
            "106208IM": "Bari",
            "106209IM": "Barletta",
            "106210IM": "Bisceglie",
            "106211IM": "Bitetto",
            "106212IM": "Bitonto",
            "106213IM": "Bitritto",
            "106214IM": "Brindisi",
            "106215IM": "Campi Salentina",
            "106216IM": "Canosa di Puglia",
            "106217IM": "Capurso",
            "106218IM": "Carmiano",
            "106219IM": "Carovigno",
            "106220IM": "Casamassima",
            "106221IM": "Casarano",
            "106222IM": "Cassano delle Murge",
            "106223IM": "Castellana Grotte",
            "106224IM": "Castellaneta",
            "106225IM": "Cavallino",
            "106226IM": "Ceglie Messapica",
            "106227IM": "Cerignola",
            "106228IM": "Cisternino",
            "106229IM": "Conversano",
            "106230IM": "Copertino",
            "106231IM": "Corato",
            "106232IM": "Crispiano",
            "106233IM": "Cutrofiano",
            "106234IM": "Erchie",
            "106235IM": "Fasano",
            "106236IM": "Foggia",
            "106237IM": "Francavilla Fontana",
            "106238IM": "Galatina",
            "106239IM": "Galatone",
            "106240IM": "Gallipoli",
            "106241IM": "Ginosa",
            "106242IM": "Gioia del Colle",
            "106243IM": "Giovinazzo",
            "106244IM": "Gravina in Puglia",
            "106245IM": "Grottaglie",
            "106246IM": "Grumo Appula",
            "106247IM": "Laterza",
            "106248IM": "Latiano",
            "106249IM": "Lecce",
            "106250IM": "Leverano",
            "106251IM": "Lizzanello",
            "106252IM": "Lizzano",
            "106253IM": "Locorotondo",
            "106254IM": "Lucera",
            "106255IM": "Maglie",
            "106256IM": "Manduria",
            "106257IM": "Manfredonia",
            "106258IM": "Margherita di Savoia",
            "106259IM": "Martano",
            "106260IM": "Martina Franca",
            "106261IM": "Massafra",
            "106262IM": "Matino",
            "106263IM": "Melendugno",
            "106264IM": "Mesagne",
            "106265IM": "Minervino Murge",
            "106266IM": "Modugno",
            "106267IM": "Mola di Bari",
            "106268IM": "Molfetta",
            "106269IM": "Monopoli",
            "106270IM": "Monte Sant\\'Angelo",
            "106271IM": "Monteroni di Lecce",
            "106272IM": "Mottola",
            "106273IM": "Nardo",
            "106274IM": "Neviano",
            "106275IM": "Noci",
            "106276IM": "Noicattaro",
            "106277IM": "Novoli",
            "106278IM": "Oria",
            "106279IM": "Orta Nova",
            "106280IM": "Ostuni",
            "106281IM": "Palagiano",
            "106282IM": "Palo del Colle",
            "106283IM": "Parabita",
            "106284IM": "Polignano a Mare",
            "106285IM": "Pulsano",
            "106286IM": "Putignano"
        }
    },
    "107IM": {
        "name": "Port Saint Mary",
        "sub": {
            "107201IM": "Acquaviva delle Fonti",
            "107202IM": "Adelfia",
            "107203IM": "Alberobello",
            "107204IM": "Altamura",
            "107205IM": "Andria",
            "107206IM": "Apricena",
            "107207IM": "Aradeo",
            "107208IM": "Bari",
            "107209IM": "Barletta",
            "107210IM": "Bisceglie",
            "107211IM": "Bitetto",
            "107212IM": "Bitonto",
            "107213IM": "Bitritto",
            "107214IM": "Brindisi",
            "107215IM": "Campi Salentina",
            "107216IM": "Canosa di Puglia",
            "107217IM": "Capurso",
            "107218IM": "Carmiano",
            "107219IM": "Carovigno",
            "107220IM": "Casamassima",
            "107221IM": "Casarano",
            "107222IM": "Cassano delle Murge",
            "107223IM": "Castellana Grotte",
            "107224IM": "Castellaneta",
            "107225IM": "Cavallino",
            "107226IM": "Ceglie Messapica",
            "107227IM": "Cerignola",
            "107228IM": "Cisternino",
            "107229IM": "Conversano",
            "107230IM": "Copertino",
            "107231IM": "Corato",
            "107232IM": "Crispiano",
            "107233IM": "Cutrofiano",
            "107234IM": "Erchie",
            "107235IM": "Fasano",
            "107236IM": "Foggia",
            "107237IM": "Francavilla Fontana",
            "107238IM": "Galatina",
            "107239IM": "Galatone",
            "107240IM": "Gallipoli",
            "107241IM": "Ginosa",
            "107242IM": "Gioia del Colle",
            "107243IM": "Giovinazzo",
            "107244IM": "Gravina in Puglia",
            "107245IM": "Grottaglie",
            "107246IM": "Grumo Appula",
            "107247IM": "Laterza",
            "107248IM": "Latiano",
            "107249IM": "Lecce",
            "107250IM": "Leverano",
            "107251IM": "Lizzanello",
            "107252IM": "Lizzano",
            "107253IM": "Locorotondo",
            "107254IM": "Lucera",
            "107255IM": "Maglie",
            "107256IM": "Manduria",
            "107257IM": "Manfredonia",
            "107258IM": "Margherita di Savoia",
            "107259IM": "Martano",
            "107260IM": "Martina Franca",
            "107261IM": "Massafra",
            "107262IM": "Matino",
            "107263IM": "Melendugno",
            "107264IM": "Mesagne",
            "107265IM": "Minervino Murge",
            "107266IM": "Modugno",
            "107267IM": "Mola di Bari",
            "107268IM": "Molfetta",
            "107269IM": "Monopoli",
            "107270IM": "Monte Sant\\'Angelo",
            "107271IM": "Monteroni di Lecce",
            "107272IM": "Mottola",
            "107273IM": "Nardo",
            "107274IM": "Neviano",
            "107275IM": "Noci",
            "107276IM": "Noicattaro",
            "107277IM": "Novoli",
            "107278IM": "Oria",
            "107279IM": "Orta Nova",
            "107280IM": "Ostuni",
            "107281IM": "Palagiano",
            "107282IM": "Palo del Colle",
            "107283IM": "Parabita",
            "107284IM": "Polignano a Mare",
            "107285IM": "Pulsano",
            "107286IM": "Putignano"
        }
    },
    "108IM": {
        "name": "Ramsey",
        "sub": {
            "108201IM": "Acquaviva delle Fonti",
            "108202IM": "Adelfia",
            "108203IM": "Alberobello",
            "108204IM": "Altamura",
            "108205IM": "Andria",
            "108206IM": "Apricena",
            "108207IM": "Aradeo",
            "108208IM": "Bari",
            "108209IM": "Barletta",
            "108210IM": "Bisceglie",
            "108211IM": "Bitetto",
            "108212IM": "Bitonto",
            "108213IM": "Bitritto",
            "108214IM": "Brindisi",
            "108215IM": "Campi Salentina",
            "108216IM": "Canosa di Puglia",
            "108217IM": "Capurso",
            "108218IM": "Carmiano",
            "108219IM": "Carovigno",
            "108220IM": "Casamassima",
            "108221IM": "Casarano",
            "108222IM": "Cassano delle Murge",
            "108223IM": "Castellana Grotte",
            "108224IM": "Castellaneta",
            "108225IM": "Cavallino",
            "108226IM": "Ceglie Messapica",
            "108227IM": "Cerignola",
            "108228IM": "Cisternino",
            "108229IM": "Conversano",
            "108230IM": "Copertino",
            "108231IM": "Corato",
            "108232IM": "Crispiano",
            "108233IM": "Cutrofiano",
            "108234IM": "Erchie",
            "108235IM": "Fasano",
            "108236IM": "Foggia",
            "108237IM": "Francavilla Fontana",
            "108238IM": "Galatina",
            "108239IM": "Galatone",
            "108240IM": "Gallipoli",
            "108241IM": "Ginosa",
            "108242IM": "Gioia del Colle",
            "108243IM": "Giovinazzo",
            "108244IM": "Gravina in Puglia",
            "108245IM": "Grottaglie",
            "108246IM": "Grumo Appula",
            "108247IM": "Laterza",
            "108248IM": "Latiano",
            "108249IM": "Lecce",
            "108250IM": "Leverano",
            "108251IM": "Lizzanello",
            "108252IM": "Lizzano",
            "108253IM": "Locorotondo",
            "108254IM": "Lucera",
            "108255IM": "Maglie",
            "108256IM": "Manduria",
            "108257IM": "Manfredonia",
            "108258IM": "Margherita di Savoia",
            "108259IM": "Martano",
            "108260IM": "Martina Franca",
            "108261IM": "Massafra",
            "108262IM": "Matino",
            "108263IM": "Melendugno",
            "108264IM": "Mesagne",
            "108265IM": "Minervino Murge",
            "108266IM": "Modugno",
            "108267IM": "Mola di Bari",
            "108268IM": "Molfetta",
            "108269IM": "Monopoli",
            "108270IM": "Monte Sant\\'Angelo",
            "108271IM": "Monteroni di Lecce",
            "108272IM": "Mottola",
            "108273IM": "Nardo",
            "108274IM": "Neviano",
            "108275IM": "Noci",
            "108276IM": "Noicattaro",
            "108277IM": "Novoli",
            "108278IM": "Oria",
            "108279IM": "Orta Nova",
            "108280IM": "Ostuni",
            "108281IM": "Palagiano",
            "108282IM": "Palo del Colle",
            "108283IM": "Parabita",
            "108284IM": "Polignano a Mare",
            "108285IM": "Pulsano",
            "108286IM": "Putignano"
        }
    }
}